PARyOpt/README.md
PARyOpt/__init__.py
PARyOpt/acquisition_functions.py
PARyOpt/pare.py
PARyOpt/paryopt.py
PARyOpt/utils.py
PARyOpt/evaluators/__init__.py
PARyOpt/evaluators/async.py
PARyOpt/evaluators/async_local.py
PARyOpt/evaluators/async_local_sbatch.py
PARyOpt/evaluators/async_parse_result_local.py
PARyOpt/evaluators/async_sbatch.py
PARyOpt/evaluators/connection.py
PARyOpt/evaluators/paryopt_async.py
PARyOpt/kernel/__init__.py
PARyOpt/kernel/kernel_function.py
PARyOpt/kernel/matern.py
PARyOpt/kernel/squared_exponential.py
PARyOpt-1.0.2.2.dist-info/LICENSE.MIT
PARyOpt-1.0.2.2.dist-info/METADATA
PARyOpt-1.0.2.2.dist-info/WHEEL
PARyOpt-1.0.2.2.dist-info/top_level.txt
PARyOpt-1.0.2.2.dist-info/RECORD
