Metadata-Version: 2.1
Name: PARyOpt
Version: 1.0.2.2
Summary: A flexible Bayesian optimization framework.
Home-page: https://bitbucket.org/baskargroup/paryopt
Author: Balaji Pokuri
Author-email: balajip@iastate.edu
Maintainer: Balaji Pokuri
Maintainer-email: balajip@iastate.edu
License: LICENSE.txt
Project-URL: Documentation, https://paryopt.rtfd.io
Project-URL: Source, https://bitbucket.org/baskargroup/paryopt
Project-URL: Tracker, https://bitbucket.org/baskargroup/paryopt/issues
Platform: UNKNOWN
Classifier: Programming Language :: Python :: 3.5
Classifier: Programming Language :: Python :: 3.6
Classifier: Programming Language :: Python :: 3.7
Classifier: Programming Language :: Python :: 3.8
Classifier: License :: OSI Approved :: MIT License
Classifier: Operating System :: OS Independent
Classifier: Natural Language :: English
Classifier: Topic :: Scientific/Engineering
Requires-Python: >=3.5
Requires-Dist: numpy (>=1.14.3)
Requires-Dist: paramiko (<3,>=2.6.1)
Requires-Dist: scipy (>=1.4.1)
Requires-Dist: sphinx (==4.3.1)
Provides-Extra: allow_executing_parse_result_functions_directly_on_remote_hosts
Requires-Dist: dill (>=0.2.5); extra == 'allow_executing_parse_result_functions_directly_on_remote_hosts'
Provides-Extra: for_visualization
Requires-Dist: matplotlib (>=3.0.0); extra == 'for_visualization'
